img2svg/__init__.py
img2svg/bin.py
img2svg/core.py
img2svg/util.py
img2svg/version.json
img2svg-1.0.2.dist-info/METADATA
img2svg-1.0.2.dist-info/WHEEL
img2svg-1.0.2.dist-info/entry_points.txt
img2svg-1.0.2.dist-info/top_level.txt
img2svg-1.0.2.dist-info/RECORD
